{
    "name": {
        "common": "Zimbabwe",
        "official": "Republic of Zimbabwe",
        "nativeName": {
            "bwg": {
                "official": "Republic of Zimbabwe",
                "common": "Zimbabwe"
            },
            "eng": {
                "official": "Republic of Zimbabwe",
                "common": "Zimbabwe"
            },
            "kck": {
                "official": "Republic of Zimbabwe",
                "common": "Zimbabwe"
            },
            "khi": {
                "official": "Republic of Zimbabwe",
                "common": "Zimbabwe"
            },
            "ndc": {
                "official": "Republic of Zimbabwe",
                "common": "Zimbabwe"
            },
            "nde": {
                "official": "Republic of Zimbabwe",
                "common": "Zimbabwe"
            },
            "nya": {
                "official": "Republic of Zimbabwe",
                "common": "Zimbabwe"
            },
            "sna": {
                "official": "Republic of Zimbabwe",
                "common": "Zimbabwe"
            },
            "sot": {
                "official": "Republic of Zimbabwe",
                "common": "Zimbabwe"
            },
            "toi": {
                "official": "Republic of Zimbabwe",
                "common": "Zimbabwe"
            },
            "tsn": {
                "official": "Republic of Zimbabwe",
                "common": "Zimbabwe"
            },
            "tso": {
                "official": "Republic of Zimbabwe",
                "common": "Zimbabwe"
            },
            "ven": {
                "official": "Republic of Zimbabwe",
                "common": "Zimbabwe"
            },
            "xho": {
                "official": "Republic of Zimbabwe",
                "common": "Zimbabwe"
            },
            "zib": {
                "official": "Republic of Zimbabwe",
                "common": "Zimbabwe"
            }
        }
    },
    "tld": [
        ".zw"
    ],
    "cca2": "ZW",
    "ccn3": "716",
    "cca3": "ZWE",
    "cioc": "ZIM",
    "independent": true,
    "status": "officially-assigned",
    "unMember": true,
    "currencies": {
        "ZWL": {
            "name": "Zimbabwean dollar",
            "symbol": "$"
        }
    },
    "idd": {
        "root": "+2",
        "suffixes": [
            "63"
        ]
    },
    "capital": [
        "Harare"
    ],
    "altSpellings": [
        "ZW",
        "Republic of Zimbabwe"
    ],
    "region": "Africa",
    "subregion": "Southern Africa",
    "languages": {
        "bwg": "Chibarwe",
        "eng": "English",
        "kck": "Kalanga",
        "khi": "Khoisan",
        "ndc": "Ndau",
        "nde": "Northern Ndebele",
        "nya": "Chewa",
        "sna": "Shona",
        "sot": "Sotho",
        "toi": "Tonga",
        "tsn": "Tswana",
        "tso": "Tsonga",
        "ven": "Venda",
        "xho": "Xhosa",
        "zib": "Zimbabwean Sign Language"
    },
    "translations": {
        "ara": {
            "official": "جمهورية زيمبابوي",
            "common": "زيمبابوي"
        },
        "bre": {
            "official": "Republik Zimbabwe",
            "common": "Zimbabwe"
        },
        "ces": {
            "official": "Zimbabwská republika",
            "common": "Zimbabwe"
        },
        "cym": {
            "official": "Republic of Zimbabwe",
            "common": "Zimbabwe"
        },
        "deu": {
            "official": "Republik Simbabwe",
            "common": "Simbabwe"
        },
        "est": {
            "official": "Zimbabwe Vabariik",
            "common": "Zimbabwe"
        },
        "fin": {
            "official": "Zimbabwen tasavalta",
            "common": "Zimbabwe"
        },
        "fra": {
            "official": "République du Zimbabwe",
            "common": "Zimbabwe"
        },
        "hrv": {
            "official": "Republika Zimbabve",
            "common": "Zimbabve"
        },
        "hun": {
            "official": "Zimbabwei Köztársaság",
            "common": "Zimbabwe"
        },
        "ita": {
            "official": "Repubblica dello Zimbabwe",
            "common": "Zimbabwe"
        },
        "jpn": {
            "official": "ジンバブエ共和国",
            "common": "ジンバブエ"
        },
        "kor": {
            "official": "짐바브웨 공화국",
            "common": "짐바브웨"
        },
        "nld": {
            "official": "Republiek Zimbabwe",
            "common": "Zimbabwe"
        },
        "per": {
            "official": "جمهوری زیمبابوه",
            "common": "زیمبابوه"
        },
        "pol": {
            "official": "Republika Zimbabwe",
            "common": "Zimbabwe"
        },
        "por": {
            "official": "República do Zimbabwe",
            "common": "Zimbabwe"
        },
        "rus": {
            "official": "Республика Зимбабве",
            "common": "Зимбабве"
        },
        "slk": {
            "official": "Zimbabwianska republika",
            "common": "Zimbabwe"
        },
        "spa": {
            "official": "República de Zimbabue",
            "common": "Zimbabue"
        },
        "swe": {
            "official": "Republiken Zimbabwe",
            "common": "Zimbabwe"
        },
        "tur": {
            "official": "Zimbabve Cumhuriyeti",
            "common": "Zimbabve"
        },
        "urd": {
            "official": "جمہوریہ زمبابوے",
            "common": "زمبابوے"
        },
        "zho": {
            "official": "津巴布韦共和国",
            "common": "津巴布韦"
        }
    },
    "latlng": [
        -20,
        30
    ],
    "landlocked": true,
    "borders": [
        "BWA",
        "MOZ",
        "ZAF",
        "ZMB"
    ],
    "area": 390757,
    "demonyms": {
        "eng": {
            "f": "Zimbabwean",
            "m": "Zimbabwean"
        },
        "fra": {
            "f": "Zimbabwéenne",
            "m": "Zimbabwéen"
        }
    },
    "flag": "🇿🇼",
    "maps": {
        "googleMaps": "https://goo.gl/maps/M26BqdwQctqxXS65A",
        "openStreetMaps": "https://www.openstreetmap.org/relation/195272"
    },
    "population": 14862927,
    "gini": {
        "2019": 50.3
    },
    "fifa": "ZIM",
    "car": {
        "signs": [
            "ZW"
        ],
        "side": "left"
    },
    "timezones": [
        "UTC+02:00"
    ],
    "continents": [
        "Africa"
    ],
    "flags": {
        "png": "https://flagcdn.com/w320/zw.png",
        "svg": "https://flagcdn.com/zw.svg"
    },
    "coatOfArms": {
        "png": "https://mainfacts.com/media/images/coats_of_arms/zw.png",
        "svg": "https://mainfacts.com/media/images/coats_of_arms/zw.svg"
    },
    "startOfWeek": "monday",
    "capitalInfo": {
        "latlng": [
            -17.82,
            31.03
        ]
    },
    "states": [
        {
            "name": "Bulawayo Province",
            "type": null,
            "latitude": "-20.14895050",
            "longitude": "28.53310380",
            "code": "BU"
        },
        {
            "name": "Harare Province",
            "type": null,
            "latitude": "-17.82162880",
            "longitude": "31.04922590",
            "code": "HA"
        },
        {
            "name": "Manicaland",
            "type": null,
            "latitude": "-18.92163860",
            "longitude": "32.17460500",
            "code": "MA"
        },
        {
            "name": "Mashonaland Central Province",
            "type": null,
            "latitude": "-16.76442950",
            "longitude": "31.07937050",
            "code": "MC"
        },
        {
            "name": "Mashonaland East Province",
            "type": null,
            "latitude": "-18.58716420",
            "longitude": "31.26263660",
            "code": "ME"
        },
        {
            "name": "Mashonaland West Province",
            "type": null,
            "latitude": "-17.48510290",
            "longitude": "29.78892480",
            "code": "MW"
        },
        {
            "name": "Masvingo Province",
            "type": null,
            "latitude": "-20.62415090",
            "longitude": "31.26263660",
            "code": "MV"
        },
        {
            "name": "Matabeleland North Province",
            "type": null,
            "latitude": "-18.53315660",
            "longitude": "27.54958460",
            "code": "MN"
        },
        {
            "name": "Matabeleland South Province",
            "type": null,
            "latitude": "-21.05233700",
            "longitude": "29.04599270",
            "code": "MS"
        },
        {
            "name": "Midlands Province",
            "type": null,
            "latitude": "-19.05520090",
            "longitude": "29.60354950",
            "code": "MI"
        }
    ]
}
